[
  {
    "video_name": "Halo",
    "video_image": "images/video/halo.jpg",
    "video_year": "2018",
    "video_group": "HD",
    "video_duration": "1hr 52min",
    "video_id": 1,
    "video_rating": "8.5",
    "video_info": "Halo  Sci-fi series",
    "video_src": "https://www.youtube.com/embed/nVuIgMBMGv0?si=IOhCH1o9k_qJ13hm"
  },
  {
    "video_name": "John Wick 4",
    "video_image": "images/video/johnwick.jpg",
    "video_year": "2023",
    "video_group": "HD",
    "video_duration": "1hr 46min",
    "video_id": 2,
    "video_rating": "7.2",
    "video_info": "The Ultimate Hitman",
    "video_src": "https://www.youtube.com/embed/lJyl5oHnVcU?si=9yHokD2VjF1xVarK"
  },
  {
    "video_name": "The Little Mermaid",
    "video_image": "images/video/lilmermaid.jpg",
    "video_year": "2023",
    "video_group": "4K",
    "video_duration": "1hr 29min",
    "video_id": 3,
    "video_rating": "7.9",
    "video_info": "Mermaid outta water",
    "video_src": "https://www.youtube.com/embed/b6WjuET3b8o?si=8CqMiLcQSKU2I45H"
  },
  {
    "video_name": "The Meg 2",
    "video_image": "images/video/meg2.jpg",
    "video_year": "2023",
    "video_group": "HD",
    "video_duration": "2hr 10min",
    "video_id": 4,
    "video_rating": "9.2",
    "video_info": "The trench",
    "video_src": "https://www.youtube.com/embed/zTjRbN74r3o?si=JQZkRJ5WJV-CyeMb"
  },
  {
    "video_name": "Nezha",
    "video_image": "images/video/nezha.jpeg",
    "video_year": "2023",
    "video_group": "4K",
    "video_duration": "2hr 6min",
    "video_id": 5,
    "video_rating": "9.7",
    "video_info": "Birth of the evil pill",
    "video_src": "https://www.youtube.com/embed/CcgE0RNxWJw?si=IRuTSV1VV-UXpFR2"
  },
  {
    "video_name": "Minions",
    "video_image": "images/video/minions.jpeg",
    "video_year": "2023",
    "video_group": "HD",
    "video_duration": "1hr 32min",
    "video_id": 6,
    "video_rating": "8.5",
    "video_info": "Love between Opposites",
    "video_src": "https://www.youtube.com/embed/EOB3vwnV1eQ?si=f_pDVkRRB8LOrXM3"
  },
  {
    "video_name": "Shazam 2",
    "video_image": "images/video/shazam.jpg",
    "video_year": "2023",
    "video_group": "4K",
    "video_duration": "56min",
    "video_id": 7,
    "video_rating": "7.7",
    "video_info": "Shazam",
    "video_src": "https://www.youtube.com/embed/50VWOBi0VFs?si=COiDDP-3F1XfXUJB"
  },
  {
    "video_name": "Spiderman",
    "video_image": "images/video/spiderman.jpg",
    "video_year": "2023",
    "video_group": "HD",
    "video_duration": "2hr 36min",
    "video_id": 8,
    "video_rating": "8.6",
    "video_info": "Across the multiverse",
    "video_src": "https://www.youtube.com/embed/ShZ978fBl6Y?si=0ZO7SGjy8UeXAMfb"
  },
  {
    "video_name": "The Nun",
    "video_image": "images/video/thenun.jpg",
    "video_year": "2023",
    "video_group": "HD",
    "video_duration": "2hr 51min",
    "video_id": 9,
    "video_rating": "8.5",
    "video_info": "Dead nun terror",
    "video_src": "https://www.youtube.com/embed/Fp8msa5uYsc?si=My8lQb9rO9rEB7LY"
  },
  {
    "video_name": "The Transformers",
    "video_image": "images/video/transformers.jpg",
    "video_year": "2023",
    "video_group": "4K",
    "video_duration": "2hr 17min",
    "video_id": 10,
    "video_rating": "7.9",
    "video_info": "Battle against omnicron",
    "video_src": "https://www.youtube.com/embed/IPfJnp1guPc?si=FSozy8fchcZrCpBW"
  },
  {
    "video_name": "The Transformers",
    "video_image": "images/video/transformers.jpg",
    "video_year": "2023",
    "video_group": "4K",
    "video_duration": "2hr 17min",
    "video_id": 10,
    "video_rating": "7.9",
    "video_info": "Battle against omnicron",
    "video_src": "https://www.youtube.com/embed/TFF4-b393hY?si=hbJvloudaDtzVVzT"
  },
  {
    "video_name": "The Transformers",
    "video_image": "images/video/transformers.jpg",
    "video_year": "2023",
    "video_group": "4K",
    "video_duration": "2hr 17min",
    "video_id": 10,
    "video_rating": "7.9",
    "video_info": "Battle against omnicron",
    "video_src": "https://www.youtube.com/embed/c4FLtqbYU8s?si=4z0xCbUtWlyUePc8"
  },
  {
    "video_name": "The Transformers",
    "video_image": "images/video/transformers.jpg",
    "video_year": "2023",
    "video_group": "4K",
    "video_duration": "2hr 17min",
    "video_id": 10,
    "video_rating": "7.9",
    "video_info": "Battle against omnicron",
    "video_src": "https://www.youtube.com/embed/O_saBlPL4d8?si=dUCArk7TIG26_9Do"
  },
  {
    "video_name": "The Transformers",
    "video_image": "images/video/transformers.jpg",
    "video_year": "2023",
    "video_group": "4K",
    "video_duration": "2hr 17min",
    "video_id": 10,
    "video_rating": "7.9",
    "video_info": "Battle against omnicron",
    "video_src": "https://www.youtube.com/embed/zsWUp6zp-no?si=AhImtm0ESU-Kn59g"
  },
  {
    "video_name": "The Transformers",
    "video_image": "images/video/transformers.jpg",
    "video_year": "2023",
    "video_group": "4K",
    "video_duration": "2hr 17min",
    "video_id": 10,
    "video_rating": "7.9",
    "video_info": "Battle against omnicron",
    "video_src": "https://www.youtube.com/embed/G6Cnoyyhu3o?si=aJ4CB2pF_sJIq_8C"
  },
  {
    "video_name": "The Transformers",
    "video_image": "images/video/transformers.jpg",
    "video_year": "2023",
    "video_group": "4K",
    "video_duration": "2hr 17min",
    "video_id": 10,
    "video_rating": "7.9",
    "video_info": "Battle against omnicron",
    "video_src": "https://www.youtube.com/embed/8R9wntOoFOE?si=tlvJ6q8eqndfs3rb"
  },
  {
    "video_name": "The Transformers",
    "video_image": "images/video/transformers.jpg",
    "video_year": "2023",
    "video_group": "4K",
    "video_duration": "2hr 17min",
    "video_id": 10,
    "video_rating": "7.9",
    "video_info": "Battle against omnicron",
    "video_src": "https://www.youtube.com/embed/48POqJsCC2M?si=lXsDyPFepY4kpsOj"
  },
  {
    "video_name": "The Transformers",
    "video_image": "images/video/transformers.jpg",
    "video_year": "2023",
    "video_group": "4K",
    "video_duration": "2hr 17min",
    "video_id": 10,
    "video_rating": "7.9",
    "video_info": "Battle against omnicron",
    "video_src": "https://www.youtube.com/embed/n5GO0ZiE7rU?si=Jg_kU4husriTLBRt"
  },
  {
    "video_name": "The Transformers",
    "video_image": "images/video/transformers.jpg",
    "video_year": "2023",
    "video_group": "4K",
    "video_duration": "2hr 17min",
    "video_id": 10,
    "video_rating": "7.9",
    "video_info": "Battle against omnicron",
    "video_src": "https://www.youtube.com/embed/m64t7eaKHLw?si=bQUa6VpbrvFPUdUI"
  }
]